{
    "type": "FeatureCollection",
    "features": [
        {
            "type": "Feature",
            "properties": {
                "ele": 0,
                "time": "2013/02/16 21:31:25+00",
                "name": "Hoh visitor center"
            },
            "geometry": {
                "type": "Point",
                "coordinates": [
                    -123.935094,
                    47.860546
                ]
            }
        }
    ]
}